MANIFEST.in
README.md
setup.py
stylecloud/__init__.py
stylecloud/stylecloud.py
stylecloud.egg-info/PKG-INFO
stylecloud.egg-info/SOURCES.txt
stylecloud.egg-info/dependency_links.txt
stylecloud.egg-info/entry_points.txt
stylecloud.egg-info/requires.txt
stylecloud.egg-info/top_level.txt
stylecloud/static/Staatliches-Regular.ttf
stylecloud/static/fa-brands-400.ttf
stylecloud/static/fa-regular-400.ttf
stylecloud/static/fa-solid-900.ttf
stylecloud/static/fontawesome.min.css