Metadata-Version: 2.1
Name: stylecloud
Version: 0.1.1
Summary: Python package + CLI to generate stylistic wordclouds, including gradients and icon shapes!
Home-page: https://github.com/minimaxir/stylecloud
Author: Max Woolf
Author-email: max@minimaxir.com
License: MIT
Keywords: wordcloud,data visualization,text cool stuff
Platform: UNKNOWN
Requires-Python: >=3.5
